PungeDataClean-0.1.0.dist-info/METADATA
PungeDataClean-0.1.0.dist-info/WHEEL
PungeDataClean/__init__.py
PungeDataClean/PungeDataClean.cp310-win_amd64.pyd
PungeDataClean-0.1.0.dist-info/RECORD
